{
  "koa-logger": true,
  "server": {
    "ip": "0.0.0.0",
    "port": 10086
  },
  "db": {
    "client": "mysql",
    "connection": {
      "host": "127.0.0.1",
      "user": "root",
      "password": "123456",
      "database": "merchant_cms"
    },
    "debug": true,
    "pool": {"min": 0, "max": 10},
    "acquireConnectionTimeout": 10000
  },
  "session": {
    "key": "SESSION_ID",
    "maxAge": 3600000,
    "minAge": 1800000,
    "overwrite": true,
    "httpOnly": true,
    "signed": false,
    "rolling": false,
    "renew": false
  }
}